odoo10_addon_hotel_reservation-10.0.1.0.0.99.dev21-nspkg.pth
odoo/addons/hotel_reservation/README.rst
odoo/addons/hotel_reservation/__init__.py
odoo/addons/hotel_reservation/__manifest__.py
odoo/addons/hotel_reservation/LICENSE/LICENSE
odoo/addons/hotel_reservation/data/hotel_scheduler.xml
odoo/addons/hotel_reservation/i18n/da.po
odoo/addons/hotel_reservation/i18n/es.po
odoo/addons/hotel_reservation/i18n/fr.po
odoo/addons/hotel_reservation/i18n/fr_BE.po
odoo/addons/hotel_reservation/i18n/fr_FR.po
odoo/addons/hotel_reservation/i18n/pt_BR.po
odoo/addons/hotel_reservation/i18n/sv.po
odoo/addons/hotel_reservation/models/__init__.py
odoo/addons/hotel_reservation/models/hotel_reservation.py
odoo/addons/hotel_reservation/report/__init__.py
odoo/addons/hotel_reservation/report/hotel_reservation_report.py
odoo/addons/hotel_reservation/report/hotel_reservation_report.xml
odoo/addons/hotel_reservation/security/ir.model.access.csv
odoo/addons/hotel_reservation/static/description/HotelReserv.png
odoo/addons/hotel_reservation/static/description/done.png
odoo/addons/hotel_reservation/static/description/folio.png
odoo/addons/hotel_reservation/static/description/icon.png
odoo/addons/hotel_reservation/static/description/res5.png
odoo/addons/hotel_reservation/static/description/res6.png
odoo/addons/hotel_reservation/static/description/room.png
odoo/addons/hotel_reservation/static/description/serpent.png
odoo/addons/hotel_reservation/static/src/css/room_summary.css
odoo/addons/hotel_reservation/static/src/js/hotel_room_summary.js
odoo/addons/hotel_reservation/static/src/xml/hotel_room_summary.xml
odoo/addons/hotel_reservation/tests/__init__.py
odoo/addons/hotel_reservation/tests/test_hotel_reservation.py
odoo/addons/hotel_reservation/views/email_temp_view.xml
odoo/addons/hotel_reservation/views/hotel_reservation_data.xml
odoo/addons/hotel_reservation/views/hotel_reservation_sequence.xml
odoo/addons/hotel_reservation/views/hotel_reservation_view.xml
odoo10_addon_hotel_reservation-10.0.1.0.0.99.dev21.dist-info/METADATA
odoo10_addon_hotel_reservation-10.0.1.0.0.99.dev21.dist-info/WHEEL
odoo10_addon_hotel_reservation-10.0.1.0.0.99.dev21.dist-info/namespace_packages.txt
odoo10_addon_hotel_reservation-10.0.1.0.0.99.dev21.dist-info/top_level.txt
odoo10_addon_hotel_reservation-10.0.1.0.0.99.dev21.dist-info/RECORD
